{
  "relationships_following": [
    {
      "title": "",
      "media_list_data": [
        
      ],
      "string_list_data": [
        {
          "href": "https://www.instagram.com/slumsauce",
          "value": "slumsauce",
          "timestamp": 1673161306
        }
      ]
    },
    {
      "title": "",
      "media_list_data": [
        
      ],
      "string_list_data": [
        {
          "href": "https://www.instagram.com/songhxxnah",
          "value": "songhxxnah",
          "timestamp": 1673133123
        }
      ]
    },
    {
      "title": "",
      "media_list_data": [
        
      ],
      "string_list_data": [
        {
          "href": "https://www.instagram.com/brianrondo",
          "value": "brianrondo",
          "timestamp": 1673115480
        }
      ]
    },
    {
      "title": "",
      "media_list_data": [
        
      ],
      "string_list_data": [
        {
          "href": "https://www.instagram.com/bom_nyc",
          "value": "bom_nyc",
          "timestamp": 1672798567
        }
      ]
    },
    {
      "title": "",
      "media_list_data": [
        
      ],
      "string_list_data": [
        {
          "href": "https://www.instagram.com/josercc.28",
          "value": "josercc.28",
          "timestamp": 1672516257
        }
      ]
    },
    {
      "title": "",
      "media_list_data": [
        
      ],
      "string_list_data": [
        {
          "href": "https://www.instagram.com/knpham",
          "value": "knpham",
          "timestamp": 1672468581
        }
      ]
    },
    {
      "title": "",
      "media_list_data": [
        
      ],
      "string_list_data": [
        {
          "href": "https://www.instagram.com/charlietran16",
          "value": "charlietran16",
          "timestamp": 1672466319
        }
      ]
    },
    {
      "title": "",
      "media_list_data": [
        
      ],
      "string_list_data": [
        {
          "href": "https://www.instagram.com/fernanda.s.vianna",
          "value": "fernanda.s.vianna",
          "timestamp": 1672076529
        }
      ]
    },
    {
      "title": "",
      "media_list_data": [
        
      ],
      "string_list_data": [
        {
          "href": "https://www.instagram.com/ventura.bruno_",
          "value": "ventura.bruno_",
          "timestamp": 1670698546
        }
      ]
    },
    {
      "title": "",
      "media_list_data": [
        
      ],
      "string_list_data": [
        {
          "href": "https://www.instagram.com/celeste.nguyenn",
          "value": "celeste.nguyenn",
          "timestamp": 1669761952
        }
      ]
    },
    {
      "title": "",
      "media_list_data": [
        
      ],
      "string_list_data": [
        {
          "href": "https://www.instagram.com/be__evelyn",
          "value": "be__evelyn",
          "timestamp": 1669463865
        }
      ]
    },
    {
      "title": "",
      "media_list_data": [
        
      ],
      "string_list_data": [
        {
          "href": "https://www.instagram.com/purinchun",
          "value": "purinchun",
          "timestamp": 1668793428
        }
      ]
    },
    {
      "title": "",
      "media_list_data": [
        
      ],
      "string_list_data": [
        {
          "href": "https://www.instagram.com/cjqzj22",
          "value": "cjqzj22",
          "timestamp": 1667926292
        }
      ]
    },
    {
      "title": "",
      "media_list_data": [
        
      ],
      "string_list_data": [
        {
          "href": "https://www.instagram.com/sonbaefps",
          "value": "sonbaefps",
          "timestamp": 1665377814
        }
      ]
    },
    {
      "title": "",
      "media_list_data": [
        
      ],
      "string_list_data": [
        {
          "href": "https://www.instagram.com/_annieoo",
          "value": "_annieoo",
          "timestamp": 1663473032
        }
      ]
    },
    {
      "title": "",
      "media_list_data": [
        
      ],
      "string_list_data": [
        {
          "href": "https://www.instagram.com/lima.luizf",
          "value": "lima.luizf",
          "timestamp": 1663164565
        }
      ]
    },
    {
      "title": "",
      "media_list_data": [
        
      ],
      "string_list_data": [
        {
          "href": "https://www.instagram.com/swifti777",
          "value": "swifti777",
          "timestamp": 1660315422
        }
      ]
    },
    {
      "title": "",
      "media_list_data": [
        
      ],
      "string_list_data": [
        {
          "href": "https://www.instagram.com/hamstar1",
          "value": "hamstar1",
          "timestamp": 1659926138
        }
      ]
    },
    {
      "title": "",
      "media_list_data": [
        
      ],
      "string_list_data": [
        {
          "href": "https://www.instagram.com/kathyy.huang",
          "value": "kathyy.huang",
          "timestamp": 1658672914
        }
      ]
    },
    {
      "title": "",
      "media_list_data": [
        
      ],
      "string_list_data": [
        {
          "href": "https://www.instagram.com/j_essc",
          "value": "j_essc",
          "timestamp": 1656988540
        }
      ]
    },
    {
      "title": "",
      "media_list_data": [
        
      ],
      "string_list_data": [
        {
          "href": "https://www.instagram.com/kengkeng79979",
          "value": "kengkeng79979",
          "timestamp": 1656081085
        }
      ]
    },
    {
      "title": "",
      "media_list_data": [
        
      ],
      "string_list_data": [
        {
          "href": "https://www.instagram.com/rosalie_blair",
          "value": "rosalie_blair",
          "timestamp": 1655615520
        }
      ]
    },
    {
      "title": "",
      "media_list_data": [
        
      ],
      "string_list_data": [
        {
          "href": "https://www.instagram.com/andrepelomundo",
          "value": "andrepelomundo",
          "timestamp": 1655017637
        }
      ]
    },
    {
      "title": "",
      "media_list_data": [
        
      ],
      "string_list_data": [
        {
          "href": "https://www.instagram.com/susieeebabyy",
          "value": "susieeebabyy",
          "timestamp": 1653807126
        }
      ]
    },
    {
      "title": "",
      "media_list_data": [
        
      ],
      "string_list_data": [
        {
          "href": "https://www.instagram.com/yeahheyyeh",
          "value": "yeahheyyeh",
          "timestamp": 1653022741
        }
      ]
    },
    {
      "title": "",
      "media_list_data": [
        
      ],
      "string_list_data": [
        {
          "href": "https://www.instagram.com/oliverlai55",
          "value": "oliverlai55",
          "timestamp": 1653022369
        }
      ]
    },
    {
      "title": "",
      "media_list_data": [
        
      ],
      "string_list_data": [
        {
          "href": "https://www.instagram.com/paul___chau",
          "value": "paul___chau",
          "timestamp": 1650643560
        }
      ]
    },
    {
      "title": "",
      "media_list_data": [
        
      ],
      "string_list_data": [
        {
          "href": "https://www.instagram.com/vivianstarss",
          "value": "vivianstarss",
          "timestamp": 1649573639
        }
      ]
    },
    {
      "title": "",
      "media_list_data": [
        
      ],
      "string_list_data": [
        {
          "href": "https://www.instagram.com/yadimao",
          "value": "yadimao",
          "timestamp": 1649566335
        }
      ]
    },
    {
      "title": "",
      "media_list_data": [
        
      ],
      "string_list_data": [
        {
          "href": "https://www.instagram.com/dalewang",
          "value": "dalewang",
          "timestamp": 1649463405
        }
      ]
    },
    {
      "title": "",
      "media_list_data": [
        
      ],
      "string_list_data": [
        {
          "href": "https://www.instagram.com/k_yang27",
          "value": "k_yang27",
          "timestamp": 1649409714
        }
      ]
    },
    {
      "title": "",
      "media_list_data": [
        
      ],
      "string_list_data": [
        {
          "href": "https://www.instagram.com/beta_alaurine",
          "value": "beta_alaurine",
          "timestamp": 1648773387
        }
      ]
    },
    {
      "title": "",
      "media_list_data": [
        
      ],
      "string_list_data": [
        {
          "href": "https://www.instagram.com/rosita_ayo",
          "value": "rosita_ayo",
          "timestamp": 1648420563
        }
      ]
    },
    {
      "title": "",
      "media_list_data": [
        
      ],
      "string_list_data": [
        {
          "href": "https://www.instagram.com/thanh_thanh_3",
          "value": "thanh_thanh_3",
          "timestamp": 1648420538
        }
      ]
    },
    {
      "title": "",
      "media_list_data": [
        
      ],
      "string_list_data": [
        {
          "href": "https://www.instagram.com/senesombath",
          "value": "senesombath",
          "timestamp": 1648413647
        }
      ]
    },
    {
      "title": "",
      "media_list_data": [
        
      ],
      "string_list_data": [
        {
          "href": "https://www.instagram.com/anna_s178",
          "value": "anna_s178",
          "timestamp": 1648302556
        }
      ]
    },
    {
      "title": "",
      "media_list_data": [
        
      ],
      "string_list_data": [
        {
          "href": "https://www.instagram.com/br_i_annn",
          "value": "br_i_annn",
          "timestamp": 1647963532
        }
      ]
    },
    {
      "title": "",
      "media_list_data": [
        
      ],
      "string_list_data": [
        {
          "href": "https://www.instagram.com/kdjung1396",
          "value": "kdjung1396",
          "timestamp": 1647712370
        }
      ]
    },
    {
      "title": "",
      "media_list_data": [
        
      ],
      "string_list_data": [
        {
          "href": "https://www.instagram.com/kwonsun.j",
          "value": "kwonsun.j",
          "timestamp": 1647682065
        }
      ]
    },
    {
      "title": "",
      "media_list_data": [
        
      ],
      "string_list_data": [
        {
          "href": "https://www.instagram.com/cvitlinn",
          "value": "cvitlinn",
          "timestamp": 1647151534
        }
      ]
    },
    {
      "title": "",
      "media_list_data": [
        
      ],
      "string_list_data": [
        {
          "href": "https://www.instagram.com/kira_jia",
          "value": "kira_jia",
          "timestamp": 1647069355
        }
      ]
    },
    {
      "title": "",
      "media_list_data": [
        
      ],
      "string_list_data": [
        {
          "href": "https://www.instagram.com/crystalmath99",
          "value": "crystalmath99",
          "timestamp": 1646663197
        }
      ]
    },
    {
      "title": "",
      "media_list_data": [
        
      ],
      "string_list_data": [
        {
          "href": "https://www.instagram.com/leonaito22",
          "value": "leonaito22",
          "timestamp": 1646558079
        }
      ]
    },
    {
      "title": "",
      "media_list_data": [
        
      ],
      "string_list_data": [
        {
          "href": "https://www.instagram.com/alicebyallie",
          "value": "alicebyallie",
          "timestamp": 1645859023
        }
      ]
    },
    {
      "title": "",
      "media_list_data": [
        
      ],
      "string_list_data": [
        {
          "href": "https://www.instagram.com/rachal__x",
          "value": "rachal__x",
          "timestamp": 1645348920
        }
      ]
    },
    {
      "title": "",
      "media_list_data": [
        
      ],
      "string_list_data": [
        {
          "href": "https://www.instagram.com/justinujong",
          "value": "justinujong",
          "timestamp": 1645281163
        }
      ]
    },
    {
      "title": "",
      "media_list_data": [
        
      ],
      "string_list_data": [
        {
          "href": "https://www.instagram.com/keithwillroche",
          "value": "keithwillroche",
          "timestamp": 1642989257
        }
      ]
    },
    {
      "title": "",
      "media_list_data": [
        
      ],
      "string_list_data": [
        {
          "href": "https://www.instagram.com/jayrcamba",
          "value": "jayrcamba",
          "timestamp": 1641580307
        }
      ]
    },
    {
      "title": "",
      "media_list_data": [
        
      ],
      "string_list_data": [
        {
          "href": "https://www.instagram.com/5656nomi",
          "value": "5656nomi",
          "timestamp": 1641530373
        }
      ]
    },
    {
      "title": "",
      "media_list_data": [
        
      ],
      "string_list_data": [
        {
          "href": "https://www.instagram.com/carolrizzotto",
          "value": "carolrizzotto",
          "timestamp": 1641530366
        }
      ]
    },
    {
      "title": "",
      "media_list_data": [
        
      ],
      "string_list_data": [
        {
          "href": "https://www.instagram.com/dan.leeeeeee",
          "value": "dan.leeeeeee",
          "timestamp": 1641054038
        }
      ]
    },
    {
      "title": "",
      "media_list_data": [
        
      ],
      "string_list_data": [
        {
          "href": "https://www.instagram.com/wooolster",
          "value": "wooolster",
          "timestamp": 1640404111
        }
      ]
    },
    {
      "title": "",
      "media_list_data": [
        
      ],
      "string_list_data": [
        {
          "href": "https://www.instagram.com/chefwilliamlee",
          "value": "chefwilliamlee",
          "timestamp": 1640279443
        }
      ]
    },
    {
      "title": "",
      "media_list_data": [
        
      ],
      "string_list_data": [
        {
          "href": "https://www.instagram.com/hellurrramy",
          "value": "hellurrramy",
          "timestamp": 1640013224
        }
      ]
    },
    {
      "title": "",
      "media_list_data": [
        
      ],
      "string_list_data": [
        {
          "href": "https://www.instagram.com/oheycarol",
          "value": "oheycarol",
          "timestamp": 1639972153
        }
      ]
    },
    {
      "title": "",
      "media_list_data": [
        
      ],
      "string_list_data": [
        {
          "href": "https://www.instagram.com/julzsato",
          "value": "julzsato",
          "timestamp": 1639969012
        }
      ]
    },
    {
      "title": "",
      "media_list_data": [
        
      ],
      "string_list_data": [
        {
          "href": "https://www.instagram.com/alexiisari",
          "value": "alexiisari",
          "timestamp": 1639354785
        }
      ]
    },
    {
      "title": "",
      "media_list_data": [
        
      ],
      "string_list_data": [
        {
          "href": "https://www.instagram.com/mattttyyk",
          "value": "mattttyyk",
          "timestamp": 1638053733
        }
      ]
    },
    {
      "title": "",
      "media_list_data": [
        
      ],
      "string_list_data": [
        {
          "href": "https://www.instagram.com/amberfromthesun",
          "value": "amberfromthesun",
          "timestamp": 1637987262
        }
      ]
    },
    {
      "title": "",
      "media_list_data": [
        
      ],
      "string_list_data": [
        {
          "href": "https://www.instagram.com/audrey_.c",
          "value": "audrey_.c",
          "timestamp": 1637488011
        }
      ]
    },
    {
      "title": "",
      "media_list_data": [
        
      ],
      "string_list_data": [
        {
          "href": "https://www.instagram.com/verlin17",
          "value": "verlin17",
          "timestamp": 1637478345
        }
      ]
    },
    {
      "title": "",
      "media_list_data": [
        
      ],
      "string_list_data": [
        {
          "href": "https://www.instagram.com/diasgabriel___",
          "value": "diasgabriel___",
          "timestamp": 1636821932
        }
      ]
    },
    {
      "title": "",
      "media_list_data": [
        
      ],
      "string_list_data": [
        {
          "href": "https://www.instagram.com/chdgbn",
          "value": "chdgbn",
          "timestamp": 1636144247
        }
      ]
    },
    {
      "title": "",
      "media_list_data": [
        
      ],
      "string_list_data": [
        {
          "href": "https://www.instagram.com/jase_js",
          "value": "jase_js",
          "timestamp": 1635658237
        }
      ]
    },
    {
      "title": "",
      "media_list_data": [
        
      ],
      "string_list_data": [
        {
          "href": "https://www.instagram.com/eecinnaj",
          "value": "eecinnaj",
          "timestamp": 1635007577
        }
      ]
    },
    {
      "title": "",
      "media_list_data": [
        
      ],
      "string_list_data": [
        {
          "href": "https://www.instagram.com/itzvickehhx3",
          "value": "itzvickehhx3",
          "timestamp": 1634651221
        }
      ]
    },
    {
      "title": "",
      "media_list_data": [
        
      ],
      "string_list_data": [
        {
          "href": "https://www.instagram.com/megan.liew",
          "value": "megan.liew",
          "timestamp": 1633671214
        }
      ]
    },
    {
      "title": "",
      "media_list_data": [
        
      ],
      "string_list_data": [
        {
          "href": "https://www.instagram.com/tiffanilyim",
          "value": "tiffanilyim",
          "timestamp": 1633183521
        }
      ]
    },
    {
      "title": "",
      "media_list_data": [
        
      ],
      "string_list_data": [
        {
          "href": "https://www.instagram.com/nkimm_",
          "value": "nkimm_",
          "timestamp": 1633088969
        }
      ]
    },
    {
      "title": "",
      "media_list_data": [
        
      ],
      "string_list_data": [
        {
          "href": "https://www.instagram.com/alizcherie",
          "value": "alizcherie",
          "timestamp": 1632690884
        }
      ]
    },
    {
      "title": "",
      "media_list_data": [
        
      ],
      "string_list_data": [
        {
          "href": "https://www.instagram.com/justinlam20",
          "value": "justinlam20",
          "timestamp": 1632684018
        }
      ]
    },
    {
      "title": "",
      "media_list_data": [
        
      ],
      "string_list_data": [
        {
          "href": "https://www.instagram.com/johnnyieeeeee",
          "value": "johnnyieeeeee",
          "timestamp": 1632642804
        }
      ]
    },
    {
      "title": "",
      "media_list_data": [
        
      ],
      "string_list_data": [
        {
          "href": "https://www.instagram.com/matthewliu",
          "value": "matthewliu",
          "timestamp": 1632638146
        }
      ]
    },
    {
      "title": "",
      "media_list_data": [
        
      ],
      "string_list_data": [
        {
          "href": "https://www.instagram.com/goh.lil",
          "value": "goh.lil",
          "timestamp": 1632087198
        }
      ]
    },
    {
      "title": "",
      "media_list_data": [
        
      ],
      "string_list_data": [
        {
          "href": "https://www.instagram.com/thatboyhamchoi",
          "value": "thatboyhamchoi",
          "timestamp": 1632030398
        }
      ]
    },
    {
      "title": "",
      "media_list_data": [
        
      ],
      "string_list_data": [
        {
          "href": "https://www.instagram.com/katie.ly",
          "value": "katie.ly",
          "timestamp": 1631355410
        }
      ]
    },
    {
      "title": "",
      "media_list_data": [
        
      ],
      "string_list_data": [
        {
          "href": "https://www.instagram.com/angeljianggg",
          "value": "angeljianggg",
          "timestamp": 1630247775
        }
      ]
    },
    {
      "title": "",
      "media_list_data": [
        
      ],
      "string_list_data": [
        {
          "href": "https://www.instagram.com/sofiaa_wang",
          "value": "sofiaa_wang",
          "timestamp": 1630036497
        }
      ]
    },
    {
      "title": "",
      "media_list_data": [
        
      ],
      "string_list_data": [
        {
          "href": "https://www.instagram.com/mr_kam.l",
          "value": "mr_kam.l",
          "timestamp": 1629526829
        }
      ]
    },
    {
      "title": "",
      "media_list_data": [
        
      ],
      "string_list_data": [
        {
          "href": "https://www.instagram.com/universalily",
          "value": "universalily",
          "timestamp": 1629039827
        }
      ]
    },
    {
      "title": "",
      "media_list_data": [
        
      ],
      "string_list_data": [
        {
          "href": "https://www.instagram.com/projectjdm",
          "value": "projectjdm",
          "timestamp": 1628309364
        }
      ]
    },
    {
      "title": "",
      "media_list_data": [
        
      ],
      "string_list_data": [
        {
          "href": "https://www.instagram.com/vivibarri",
          "value": "vivibarri",
          "timestamp": 1627711032
        }
      ]
    },
    {
      "title": "",
      "media_list_data": [
        
      ],
      "string_list_data": [
        {
          "href": "https://www.instagram.com/okayimanna",
          "value": "okayimanna",
          "timestamp": 1627707233
        }
      ]
    },
    {
      "title": "",
      "media_list_data": [
        
      ],
      "string_list_data": [
        {
          "href": "https://www.instagram.com/taianawang",
          "value": "taianawang",
          "timestamp": 1626739701
        }
      ]
    },
    {
      "title": "",
      "media_list_data": [
        
      ],
      "string_list_data": [
        {
          "href": "https://www.instagram.com/marianalunamout",
          "value": "marianalunamout",
          "timestamp": 1626417200
        }
      ]
    },
    {
      "title": "",
      "media_list_data": [
        
      ],
      "string_list_data": [
        {
          "href": "https://www.instagram.com/jennyangg_",
          "value": "jennyangg_",
          "timestamp": 1626018400
        }
      ]
    },
    {
      "title": "",
      "media_list_data": [
        
      ],
      "string_list_data": [
        {
          "href": "https://www.instagram.com/vivsye",
          "value": "vivsye",
          "timestamp": 1625377558
        }
      ]
    },
    {
      "title": "",
      "media_list_data": [
        
      ],
      "string_list_data": [
        {
          "href": "https://www.instagram.com/framesbyanna",
          "value": "framesbyanna",
          "timestamp": 1625193584
        }
      ]
    },
    {
      "title": "",
      "media_list_data": [
        
      ],
      "string_list_data": [
        {
          "href": "https://www.instagram.com/_danahope",
          "value": "_danahope",
          "timestamp": 1625188918
        }
      ]
    },
    {
      "title": "",
      "media_list_data": [
        
      ],
      "string_list_data": [
        {
          "href": "https://www.instagram.com/ja22e77",
          "value": "ja22e77",
          "timestamp": 1624510187
        }
      ]
    },
    {
      "title": "",
      "media_list_data": [
        
      ],
      "string_list_data": [
        {
          "href": "https://www.instagram.com/matt_jao93",
          "value": "matt_jao93",
          "timestamp": 1624159672
        }
      ]
    },
    {
      "title": "",
      "media_list_data": [
        
      ],
      "string_list_data": [
        {
          "href": "https://www.instagram.com/teresaa_isa",
          "value": "teresaa_isa",
          "timestamp": 1624088154
        }
      ]
    },
    {
      "title": "",
      "media_list_data": [
        
      ],
      "string_list_data": [
        {
          "href": "https://www.instagram.com/eddiee.zhu",
          "value": "eddiee.zhu",
          "timestamp": 1624073990
        }
      ]
    },
    {
      "title": "",
      "media_list_data": [
        
      ],
      "string_list_data": [
        {
          "href": "https://www.instagram.com/ceciliacccat",
          "value": "ceciliacccat",
          "timestamp": 1623556748
        }
      ]
    },
    {
      "title": "",
      "media_list_data": [
        
      ],
      "string_list_data": [
        {
          "href": "https://www.instagram.com/thiwarat_wm",
          "value": "thiwarat_wm",
          "timestamp": 1623497810
        }
      ]
    },
    {
      "title": "",
      "media_list_data": [
        
      ],
      "string_list_data": [
        {
          "href": "https://www.instagram.com/sandyko__",
          "value": "sandyko__",
          "timestamp": 1623480597
        }
      ]
    },
    {
      "title": "",
      "media_list_data": [
        
      ],
      "string_list_data": [
        {
          "href": "https://www.instagram.com/iamsavrose",
          "value": "iamsavrose",
          "timestamp": 1623469371
        }
      ]
    },
    {
      "title": "",
      "media_list_data": [
        
      ],
      "string_list_data": [
        {
          "href": "https://www.instagram.com/crooklynchino",
          "value": "crooklynchino",
          "timestamp": 1623468995
        }
      ]
    },
    {
      "title": "",
      "media_list_data": [
        
      ],
      "string_list_data": [
        {
          "href": "https://www.instagram.com/shikun_ting",
          "value": "shikun_ting",
          "timestamp": 1623462682
        }
      ]
    },
    {
      "title": "",
      "media_list_data": [
        
      ],
      "string_list_data": [
        {
          "href": "https://www.instagram.com/mingeekeem",
          "value": "mingeekeem",
          "timestamp": 1622952412
        }
      ]
    },
    {
      "title": "",
      "media_list_data": [
        
      ],
      "string_list_data": [
        {
          "href": "https://www.instagram.com/patricknhobbes",
          "value": "patricknhobbes",
          "timestamp": 1622951306
        }
      ]
    },
    {
      "title": "",
      "media_list_data": [
        
      ],
      "string_list_data": [
        {
          "href": "https://www.instagram.com/_j.chun_",
          "value": "_j.chun_",
          "timestamp": 1622333522
        }
      ]
    },
    {
      "title": "",
      "media_list_data": [
        
      ],
      "string_list_data": [
        {
          "href": "https://www.instagram.com/kahe.1998",
          "value": "kahe.1998",
          "timestamp": 1622273802
        }
      ]
    },
    {
      "title": "",
      "media_list_data": [
        
      ],
      "string_list_data": [
        {
          "href": "https://www.instagram.com/gunnwoopark",
          "value": "gunnwoopark",
          "timestamp": 1622131891
        }
      ]
    },
    {
      "title": "",
      "media_list_data": [
        
      ],
      "string_list_data": [
        {
          "href": "https://www.instagram.com/lvflucas",
          "value": "lvflucas",
          "timestamp": 1622047296
        }
      ]
    },
    {
      "title": "",
      "media_list_data": [
        
      ],
      "string_list_data": [
        {
          "href": "https://www.instagram.com/vivianvu.pdf",
          "value": "vivianvu.pdf",
          "timestamp": 1621783090
        }
      ]
    },
    {
      "title": "",
      "media_list_data": [
        
      ],
      "string_list_data": [
        {
          "href": "https://www.instagram.com/jjngo",
          "value": "jjngo",
          "timestamp": 1621742374
        }
      ]
    },
    {
      "title": "",
      "media_list_data": [
        
      ],
      "string_list_data": [
        {
          "href": "https://www.instagram.com/miingtastic",
          "value": "miingtastic",
          "timestamp": 1621654831
        }
      ]
    },
    {
      "title": "",
      "media_list_data": [
        
      ],
      "string_list_data": [
        {
          "href": "https://www.instagram.com/pvffy_",
          "value": "pvffy_",
          "timestamp": 1621650968
        }
      ]
    },
    {
      "title": "",
      "media_list_data": [
        
      ],
      "string_list_data": [
        {
          "href": "https://www.instagram.com/chefjihanlee",
          "value": "chefjihanlee",
          "timestamp": 1621645170
        }
      ]
    },
    {
      "title": "",
      "media_list_data": [
        
      ],
      "string_list_data": [
        {
          "href": "https://www.instagram.com/__sandyz",
          "value": "__sandyz",
          "timestamp": 1621289534
        }
      ]
    },
    {
      "title": "",
      "media_list_data": [
        
      ],
      "string_list_data": [
        {
          "href": "https://www.instagram.com/amyzhangster",
          "value": "amyzhangster",
          "timestamp": 1621222721
        }
      ]
    },
    {
      "title": "",
      "media_list_data": [
        
      ],
      "string_list_data": [
        {
          "href": "https://www.instagram.com/edwardkim__",
          "value": "edwardkim__",
          "timestamp": 1621136799
        }
      ]
    },
    {
      "title": "",
      "media_list_data": [
        
      ],
      "string_list_data": [
        {
          "href": "https://www.instagram.com/kangarooshanemd",
          "value": "kangarooshanemd",
          "timestamp": 1621135592
        }
      ]
    },
    {
      "title": "",
      "media_list_data": [
        
      ],
      "string_list_data": [
        {
          "href": "https://www.instagram.com/nikki517188",
          "value": "nikki517188",
          "timestamp": 1620867533
        }
      ]
    },
    {
      "title": "",
      "media_list_data": [
        
      ],
      "string_list_data": [
        {
          "href": "https://www.instagram.com/mbdutra2013",
          "value": "mbdutra2013",
          "timestamp": 1620824425
        }
      ]
    },
    {
      "title": "",
      "media_list_data": [
        
      ],
      "string_list_data": [
        {
          "href": "https://www.instagram.com/mrandrewfung",
          "value": "mrandrewfung",
          "timestamp": 1620757690
        }
      ]
    },
    {
      "title": "",
      "media_list_data": [
        
      ],
      "string_list_data": [
        {
          "href": "https://www.instagram.com/gavinzhouu",
          "value": "gavinzhouu",
          "timestamp": 1620459254
        }
      ]
    },
    {
      "title": "",
      "media_list_data": [
        
      ],
      "string_list_data": [
        {
          "href": "https://www.instagram.com/cko.mode",
          "value": "cko.mode",
          "timestamp": 1620280647
        }
      ]
    },
    {
      "title": "",
      "media_list_data": [
        
      ],
      "string_list_data": [
        {
          "href": "https://www.instagram.com/kapdivad",
          "value": "kapdivad",
          "timestamp": 1619880411
        }
      ]
    },
    {
      "title": "",
      "media_list_data": [
        
      ],
      "string_list_data": [
        {
          "href": "https://www.instagram.com/alvinxuzj",
          "value": "alvinxuzj",
          "timestamp": 1619860127
        }
      ]
    },
    {
      "title": "",
      "media_list_data": [
        
      ],
      "string_list_data": [
        {
          "href": "https://www.instagram.com/yxx_samurai7",
          "value": "yxx_samurai7",
          "timestamp": 1619843162
        }
      ]
    },
    {
      "title": "",
      "media_list_data": [
        
      ],
      "string_list_data": [
        {
          "href": "https://www.instagram.com/joeisboring",
          "value": "joeisboring",
          "timestamp": 1619841796
        }
      ]
    },
    {
      "title": "",
      "media_list_data": [
        
      ],
      "string_list_data": [
        {
          "href": "https://www.instagram.com/flowersbyt.shop",
          "value": "flowersbyt.shop",
          "timestamp": 1619401235
        }
      ]
    },
    {
      "title": "",
      "media_list_data": [
        
      ],
      "string_list_data": [
        {
          "href": "https://www.instagram.com/ammielin",
          "value": "ammielin",
          "timestamp": 1619337088
        }
      ]
    },
    {
      "title": "",
      "media_list_data": [
        
      ],
      "string_list_data": [
        {
          "href": "https://www.instagram.com/eugenechung",
          "value": "eugenechung",
          "timestamp": 1619330674
        }
      ]
    },
    {
      "title": "",
      "media_list_data": [
        
      ],
      "string_list_data": [
        {
          "href": "https://www.instagram.com/ameli.a",
          "value": "ameli.a",
          "timestamp": 1619328337
        }
      ]
    },
    {
      "title": "",
      "media_list_data": [
        
      ],
      "string_list_data": [
        {
          "href": "https://www.instagram.com/brandon.su__",
          "value": "brandon.su__",
          "timestamp": 1618804144
        }
      ]
    },
    {
      "title": "",
      "media_list_data": [
        
      ],
      "string_list_data": [
        {
          "href": "https://www.instagram.com/wenny_ljy",
          "value": "wenny_ljy",
          "timestamp": 1618798360
        }
      ]
    },
    {
      "title": "",
      "media_list_data": [
        
      ],
      "string_list_data": [
        {
          "href": "https://www.instagram.com/punyjuny",
          "value": "punyjuny",
          "timestamp": 1618649317
        }
      ]
    },
    {
      "title": "",
      "media_list_data": [
        
      ],
      "string_list_data": [
        {
          "href": "https://www.instagram.com/fannieszeto",
          "value": "fannieszeto",
          "timestamp": 1618642801
        }
      ]
    },
    {
      "title": "",
      "media_list_data": [
        
      ],
      "string_list_data": [
        {
          "href": "https://www.instagram.com/deesierra_",
          "value": "deesierra_",
          "timestamp": 1618045775
        }
      ]
    },
    {
      "title": "",
      "media_list_data": [
        
      ],
      "string_list_data": [
        {
          "href": "https://www.instagram.com/pkim.nyc",
          "value": "pkim.nyc",
          "timestamp": 1618025903
        }
      ]
    },
    {
      "title": "",
      "media_list_data": [
        
      ],
      "string_list_data": [
        {
          "href": "https://www.instagram.com/kshahinasi",
          "value": "kshahinasi",
          "timestamp": 1617422784
        }
      ]
    },
    {
      "title": "",
      "media_list_data": [
        
      ],
      "string_list_data": [
        {
          "href": "https://www.instagram.com/nemiel.13",
          "value": "nemiel.13",
          "timestamp": 1614959702
        }
      ]
    },
    {
      "title": "",
      "media_list_data": [
        
      ],
      "string_list_data": [
        {
          "href": "https://www.instagram.com/mminnalyh",
          "value": "mminnalyh",
          "timestamp": 1612924516
        }
      ]
    },
    {
      "title": "",
      "media_list_data": [
        
      ],
      "string_list_data": [
        {
          "href": "https://www.instagram.com/mmdcamp",
          "value": "mmdcamp",
          "timestamp": 1612546038
        }
      ]
    },
    {
      "title": "",
      "media_list_data": [
        
      ],
      "string_list_data": [
        {
          "href": "https://www.instagram.com/actual_alli",
          "value": "actual_alli",
          "timestamp": 1610597434
        }
      ]
    },
    {
      "title": "",
      "media_list_data": [
        
      ],
      "string_list_data": [
        {
          "href": "https://www.instagram.com/jimmycaoo",
          "value": "jimmycaoo",
          "timestamp": 1610589498
        }
      ]
    },
    {
      "title": "",
      "media_list_data": [
        
      ],
      "string_list_data": [
        {
          "href": "https://www.instagram.com/hazmatmedic529",
          "value": "hazmatmedic529",
          "timestamp": 1608734224
        }
      ]
    },
    {
      "title": "",
      "media_list_data": [
        
      ],
      "string_list_data": [
        {
          "href": "https://www.instagram.com/dkwong.mb",
          "value": "dkwong.mb",
          "timestamp": 1608429536
        }
      ]
    },
    {
      "title": "",
      "media_list_data": [
        
      ],
      "string_list_data": [
        {
          "href": "https://www.instagram.com/carissa_hanafi",
          "value": "carissa_hanafi",
          "timestamp": 1608393541
        }
      ]
    },
    {
      "title": "",
      "media_list_data": [
        
      ],
      "string_list_data": [
        {
          "href": "https://www.instagram.com/steven0750.io",
          "value": "steven0750.io",
          "timestamp": 1608085594
        }
      ]
    },
    {
      "title": "",
      "media_list_data": [
        
      ],
      "string_list_data": [
        {
          "href": "https://www.instagram.com/kimmsnaomi",
          "value": "kimmsnaomi",
          "timestamp": 1607761780
        }
      ]
    },
    {
      "title": "",
      "media_list_data": [
        
      ],
      "string_list_data": [
        {
          "href": "https://www.instagram.com/jcheunggg",
          "value": "jcheunggg",
          "timestamp": 1607751235
        }
      ]
    },
    {
      "title": "",
      "media_list_data": [
        
      ],
      "string_list_data": [
        {
          "href": "https://www.instagram.com/yes.elvis",
          "value": "yes.elvis",
          "timestamp": 1607216034
        }
      ]
    },
    {
      "title": "",
      "media_list_data": [
        
      ],
      "string_list_data": [
        {
          "href": "https://www.instagram.com/followthentrain",
          "value": "followthentrain",
          "timestamp": 1607110722
        }
      ]
    },
    {
      "title": "",
      "media_list_data": [
        
      ],
      "string_list_data": [
        {
          "href": "https://www.instagram.com/deathcabforcuties_",
          "value": "deathcabforcuties_",
          "timestamp": 1606757796
        }
      ]
    },
    {
      "title": "",
      "media_list_data": [
        
      ],
      "string_list_data": [
        {
          "href": "https://www.instagram.com/calwoon",
          "value": "calwoon",
          "timestamp": 1606417966
        }
      ]
    },
    {
      "title": "",
      "media_list_data": [
        
      ],
      "string_list_data": [
        {
          "href": "https://www.instagram.com/helena_wuuuuu",
          "value": "helena_wuuuuu",
          "timestamp": 1605975861
        }
      ]
    },
    {
      "title": "",
      "media_list_data": [
        
      ],
      "string_list_data": [
        {
          "href": "https://www.instagram.com/matt___li",
          "value": "matt___li",
          "timestamp": 1605345990
        }
      ]
    },
    {
      "title": "",
      "media_list_data": [
        
      ],
      "string_list_data": [
        {
          "href": "https://www.instagram.com/excendence",
          "value": "excendence",
          "timestamp": 1604192994
        }
      ]
    },
    {
      "title": "",
      "media_list_data": [
        
      ],
      "string_list_data": [
        {
          "href": "https://www.instagram.com/veevacious",
          "value": "veevacious",
          "timestamp": 1604135543
        }
      ]
    },
    {
      "title": "",
      "media_list_data": [
        
      ],
      "string_list_data": [
        {
          "href": "https://www.instagram.com/tonykuoc",
          "value": "tonykuoc",
          "timestamp": 1604131197
        }
      ]
    },
    {
      "title": "",
      "media_list_data": [
        
      ],
      "string_list_data": [
        {
          "href": "https://www.instagram.com/emszhang",
          "value": "emszhang",
          "timestamp": 1604129318
        }
      ]
    },
    {
      "title": "",
      "media_list_data": [
        
      ],
      "string_list_data": [
        {
          "href": "https://www.instagram.com/aperolllllll",
          "value": "aperolllllll",
          "timestamp": 1604017631
        }
      ]
    },
    {
      "title": "",
      "media_list_data": [
        
      ],
      "string_list_data": [
        {
          "href": "https://www.instagram.com/__myyyyy__",
          "value": "__myyyyy__",
          "timestamp": 1604014755
        }
      ]
    },
    {
      "title": "",
      "media_list_data": [
        
      ],
      "string_list_data": [
        {
          "href": "https://www.instagram.com/adriana_sshi",
          "value": "adriana_sshi",
          "timestamp": 1604014679
        }
      ]
    },
    {
      "title": "",
      "media_list_data": [
        
      ],
      "string_list_data": [
        {
          "href": "https://www.instagram.com/lucasmaiacarneiro",
          "value": "lucasmaiacarneiro",
          "timestamp": 1604001211
        }
      ]
    },
    {
      "title": "",
      "media_list_data": [
        
      ],
      "string_list_data": [
        {
          "href": "https://www.instagram.com/vivianesun",
          "value": "vivianesun",
          "timestamp": 1603908423
        }
      ]
    },
    {
      "title": "",
      "media_list_data": [
        
      ],
      "string_list_data": [
        {
          "href": "https://www.instagram.com/bk47n",
          "value": "bk47n",
          "timestamp": 1603673244
        }
      ]
    },
    {
      "title": "",
      "media_list_data": [
        
      ],
      "string_list_data": [
        {
          "href": "https://www.instagram.com/andy_x_cheung",
          "value": "andy_x_cheung",
          "timestamp": 1603641590
        }
      ]
    },
    {
      "title": "",
      "media_list_data": [
        
      ],
      "string_list_data": [
        {
          "href": "https://www.instagram.com/chloelimy",
          "value": "chloelimy",
          "timestamp": 1603599052
        }
      ]
    },
    {
      "title": "",
      "media_list_data": [
        
      ],
      "string_list_data": [
        {
          "href": "https://www.instagram.com/derekdee",
          "value": "derekdee",
          "timestamp": 1603596080
        }
      ]
    },
    {
      "title": "",
      "media_list_data": [
        
      ],
      "string_list_data": [
        {
          "href": "https://www.instagram.com/__xwing",
          "value": "__xwing",
          "timestamp": 1603432599
        }
      ]
    },
    {
      "title": "",
      "media_list_data": [
        
      ],
      "string_list_data": [
        {
          "href": "https://www.instagram.com/macck.ws",
          "value": "macck.ws",
          "timestamp": 1603010295
        }
      ]
    },
    {
      "title": "",
      "media_list_data": [
        
      ],
      "string_list_data": [
        {
          "href": "https://www.instagram.com/harchurng",
          "value": "harchurng",
          "timestamp": 1603010288
        }
      ]
    },
    {
      "title": "",
      "media_list_data": [
        
      ],
      "string_list_data": [
        {
          "href": "https://www.instagram.com/woowryan",
          "value": "woowryan",
          "timestamp": 1603006240
        }
      ]
    },
    {
      "title": "",
      "media_list_data": [
        
      ],
      "string_list_data": [
        {
          "href": "https://www.instagram.com/xx0818megx",
          "value": "xx0818megx",
          "timestamp": 1603001141
        }
      ]
    },
    {
      "title": "",
      "media_list_data": [
        
      ],
      "string_list_data": [
        {
          "href": "https://www.instagram.com/a_superman",
          "value": "a_superman",
          "timestamp": 1602640479
        }
      ]
    },
    {
      "title": "",
      "media_list_data": [
        
      ],
      "string_list_data": [
        {
          "href": "https://www.instagram.com/_hermanliu",
          "value": "_hermanliu",
          "timestamp": 1602550287
        }
      ]
    },
    {
      "title": "",
      "media_list_data": [
        
      ],
      "string_list_data": [
        {
          "href": "https://www.instagram.com/bing.chillingg",
          "value": "bing.chillingg",
          "timestamp": 1602472686
        }
      ]
    },
    {
      "title": "",
      "media_list_data": [
        
      ],
      "string_list_data": [
        {
          "href": "https://www.instagram.com/t.eena",
          "value": "t.eena",
          "timestamp": 1602405783
        }
      ]
    },
    {
      "title": "",
      "media_list_data": [
        
      ],
      "string_list_data": [
        {
          "href": "https://www.instagram.com/misvngg",
          "value": "misvngg",
          "timestamp": 1602403695
        }
      ]
    },
    {
      "title": "",
      "media_list_data": [
        
      ],
      "string_list_data": [
        {
          "href": "https://www.instagram.com/k.lyw_",
          "value": "k.lyw_",
          "timestamp": 1602399884
        }
      ]
    },
    {
      "title": "",
      "media_list_data": [
        
      ],
      "string_list_data": [
        {
          "href": "https://www.instagram.com/justin.t16",
          "value": "justin.t16",
          "timestamp": 1602399023
        }
      ]
    },
    {
      "title": "",
      "media_list_data": [
        
      ],
      "string_list_data": [
        {
          "href": "https://www.instagram.com/gumbobear",
          "value": "gumbobear",
          "timestamp": 1602384389
        }
      ]
    },
    {
      "title": "",
      "media_list_data": [
        
      ],
      "string_list_data": [
        {
          "href": "https://www.instagram.com/panos.ale",
          "value": "panos.ale",
          "timestamp": 1601835049
        }
      ]
    },
    {
      "title": "",
      "media_list_data": [
        
      ],
      "string_list_data": [
        {
          "href": "https://www.instagram.com/noree.nyc",
          "value": "noree.nyc",
          "timestamp": 1601144371
        }
      ]
    },
    {
      "title": "",
      "media_list_data": [
        
      ],
      "string_list_data": [
        {
          "href": "https://www.instagram.com/annnaluuu",
          "value": "annnaluuu",
          "timestamp": 1601097955
        }
      ]
    },
    {
      "title": "",
      "media_list_data": [
        
      ],
      "string_list_data": [
        {
          "href": "https://www.instagram.com/kwan_wck_fd",
          "value": "kwan_wck_fd",
          "timestamp": 1600616917
        }
      ]
    },
    {
      "title": "",
      "media_list_data": [
        
      ],
      "string_list_data": [
        {
          "href": "https://www.instagram.com/biexiabbbbb",
          "value": "biexiabbbbb",
          "timestamp": 1599920768
        }
      ]
    },
    {
      "title": "",
      "media_list_data": [
        
      ],
      "string_list_data": [
        {
          "href": "https://www.instagram.com/syungli0824",
          "value": "syungli0824",
          "timestamp": 1599875564
        }
      ]
    },
    {
      "title": "",
      "media_list_data": [
        
      ],
      "string_list_data": [
        {
          "href": "https://www.instagram.com/sam__mei",
          "value": "sam__mei",
          "timestamp": 1599515842
        }
      ]
    },
    {
      "title": "",
      "media_list_data": [
        
      ],
      "string_list_data": [
        {
          "href": "https://www.instagram.com/debooboox3",
          "value": "debooboox3",
          "timestamp": 1599487089
        }
      ]
    },
    {
      "title": "",
      "media_list_data": [
        
      ],
      "string_list_data": [
        {
          "href": "https://www.instagram.com/tink3rr",
          "value": "tink3rr",
          "timestamp": 1599381185
        }
      ]
    },
    {
      "title": "",
      "media_list_data": [
        
      ],
      "string_list_data": [
        {
          "href": "https://www.instagram.com/eddwhaat",
          "value": "eddwhaat",
          "timestamp": 1599372848
        }
      ]
    },
    {
      "title": "",
      "media_list_data": [
        
      ],
      "string_list_data": [
        {
          "href": "https://www.instagram.com/andrewjfung",
          "value": "andrewjfung",
          "timestamp": 1599370540
        }
      ]
    },
    {
      "title": "",
      "media_list_data": [
        
      ],
      "string_list_data": [
        {
          "href": "https://www.instagram.com/davidbfung",
          "value": "davidbfung",
          "timestamp": 1599369767
        }
      ]
    },
    {
      "title": "",
      "media_list_data": [
        
      ],
      "string_list_data": [
        {
          "href": "https://www.instagram.com/riaruiz.jpg",
          "value": "riaruiz.jpg",
          "timestamp": 1599272270
        }
      ]
    },
    {
      "title": "",
      "media_list_data": [
        
      ],
      "string_list_data": [
        {
          "href": "https://www.instagram.com/jae.lee01",
          "value": "jae.lee01",
          "timestamp": 1599177692
        }
      ]
    },
    {
      "title": "",
      "media_list_data": [
        
      ],
      "string_list_data": [
        {
          "href": "https://www.instagram.com/_hermanho",
          "value": "_hermanho",
          "timestamp": 1598684367
        }
      ]
    },
    {
      "title": "",
      "media_list_data": [
        
      ],
      "string_list_data": [
        {
          "href": "https://www.instagram.com/alanlouie_realestate",
          "value": "alanlouie_realestate",
          "timestamp": 1598077037
        }
      ]
    },
    {
      "title": "",
      "media_list_data": [
        
      ],
      "string_list_data": [
        {
          "href": "https://www.instagram.com/baron_bsmnt",
          "value": "baron_bsmnt",
          "timestamp": 1597570090
        }
      ]
    },
    {
      "title": "",
      "media_list_data": [
        
      ],
      "string_list_data": [
        {
          "href": "https://www.instagram.com/fvcknekro",
          "value": "fvcknekro",
          "timestamp": 1597553463
        }
      ]
    },
    {
      "title": "",
      "media_list_data": [
        
      ],
      "string_list_data": [
        {
          "href": "https://www.instagram.com/petajai",
          "value": "petajai",
          "timestamp": 1597550017
        }
      ]
    },
    {
      "title": "",
      "media_list_data": [
        
      ],
      "string_list_data": [
        {
          "href": "https://www.instagram.com/david_gnow",
          "value": "david_gnow",
          "timestamp": 1597523434
        }
      ]
    },
    {
      "title": "",
      "media_list_data": [
        
      ],
      "string_list_data": [
        {
          "href": "https://www.instagram.com/kkeennllyyllaauu",
          "value": "kkeennllyyllaauu",
          "timestamp": 1597455251
        }
      ]
    },
    {
      "title": "",
      "media_list_data": [
        
      ],
      "string_list_data": [
        {
          "href": "https://www.instagram.com/csyqu",
          "value": "csyqu",
          "timestamp": 1597119329
        }
      ]
    },
    {
      "title": "",
      "media_list_data": [
        
      ],
      "string_list_data": [
        {
          "href": "https://www.instagram.com/marrrrrrias",
          "value": "marrrrrrias",
          "timestamp": 1595086293
        }
      ]
    },
    {
      "title": "",
      "media_list_data": [
        
      ],
      "string_list_data": [
        {
          "href": "https://www.instagram.com/imjustinho",
          "value": "imjustinho",
          "timestamp": 1593802219
        }
      ]
    },
    {
      "title": "",
      "media_list_data": [
        
      ],
      "string_list_data": [
        {
          "href": "https://www.instagram.com/luonidas",
          "value": "luonidas",
          "timestamp": 1592496854
        }
      ]
    },
    {
      "title": "",
      "media_list_data": [
        
      ],
      "string_list_data": [
        {
          "href": "https://www.instagram.com/aduhmbyu",
          "value": "aduhmbyu",
          "timestamp": 1591845308
        }
      ]
    },
    {
      "title": "",
      "media_list_data": [
        
      ],
      "string_list_data": [
        {
          "href": "https://www.instagram.com/leticia_brasilc",
          "value": "leticia_brasilc",
          "timestamp": 1591836110
        }
      ]
    },
    {
      "title": "",
      "media_list_data": [
        
      ],
      "string_list_data": [
        {
          "href": "https://www.instagram.com/imcc1004",
          "value": "imcc1004",
          "timestamp": 1585540003
        }
      ]
    },
    {
      "title": "",
      "media_list_data": [
        
      ],
      "string_list_data": [
        {
          "href": "https://www.instagram.com/carlasaviolob",
          "value": "carlasaviolob",
          "timestamp": 1581940265
        }
      ]
    },
    {
      "title": "",
      "media_list_data": [
        
      ],
      "string_list_data": [
        {
          "href": "https://www.instagram.com/yosoymurillo",
          "value": "yosoymurillo",
          "timestamp": 1579485778
        }
      ]
    },
    {
      "title": "",
      "media_list_data": [
        
      ],
      "string_list_data": [
        {
          "href": "https://www.instagram.com/amandagusmao.arq",
          "value": "amandagusmao.arq",
          "timestamp": 1578592944
        }
      ]
    },
    {
      "title": "",
      "media_list_data": [
        
      ],
      "string_list_data": [
        {
          "href": "https://www.instagram.com/isabellarf27",
          "value": "isabellarf27",
          "timestamp": 1577896634
        }
      ]
    },
    {
      "title": "",
      "media_list_data": [
        
      ],
      "string_list_data": [
        {
          "href": "https://www.instagram.com/raysacleite",
          "value": "raysacleite",
          "timestamp": 1577584624
        }
      ]
    },
    {
      "title": "",
      "media_list_data": [
        
      ],
      "string_list_data": [
        {
          "href": "https://www.instagram.com/lara_melo",
          "value": "lara_melo",
          "timestamp": 1577580535
        }
      ]
    },
    {
      "title": "",
      "media_list_data": [
        
      ],
      "string_list_data": [
        {
          "href": "https://www.instagram.com/seoulgram",
          "value": "seoulgram",
          "timestamp": 1574007899
        }
      ]
    },
    {
      "title": "",
      "media_list_data": [
        
      ],
      "string_list_data": [
        {
          "href": "https://www.instagram.com/koustyles",
          "value": "koustyles",
          "timestamp": 1573968230
        }
      ]
    },
    {
      "title": "",
      "media_list_data": [
        
      ],
      "string_list_data": [
        {
          "href": "https://www.instagram.com/aceofheaarts",
          "value": "aceofheaarts",
          "timestamp": 1572908462
        }
      ]
    },
    {
      "title": "",
      "media_list_data": [
        
      ],
      "string_list_data": [
        {
          "href": "https://www.instagram.com/jueungraceyun",
          "value": "jueungraceyun",
          "timestamp": 1572456171
        }
      ]
    },
    {
      "title": "",
      "media_list_data": [
        
      ],
      "string_list_data": [
        {
          "href": "https://www.instagram.com/imyurihong",
          "value": "imyurihong",
          "timestamp": 1570244285
        }
      ]
    },
    {
      "title": "",
      "media_list_data": [
        
      ],
      "string_list_data": [
        {
          "href": "https://www.instagram.com/joaofariao",
          "value": "joaofariao",
          "timestamp": 1568622026
        }
      ]
    },
    {
      "title": "",
      "media_list_data": [
        
      ],
      "string_list_data": [
        {
          "href": "https://www.instagram.com/theryandutchman",
          "value": "theryandutchman",
          "timestamp": 1568520362
        }
      ]
    },
    {
      "title": "",
      "media_list_data": [
        
      ],
      "string_list_data": [
        {
          "href": "https://www.instagram.com/antoniocapanema",
          "value": "antoniocapanema",
          "timestamp": 1568382269
        }
      ]
    },
    {
      "title": "",
      "media_list_data": [
        
      ],
      "string_list_data": [
        {
          "href": "https://www.instagram.com/papapausnz",
          "value": "papapausnz",
          "timestamp": 1568169809
        }
      ]
    },
    {
      "title": "",
      "media_list_data": [
        
      ],
      "string_list_data": [
        {
          "href": "https://www.instagram.com/catncradle",
          "value": "catncradle",
          "timestamp": 1567919114
        }
      ]
    },
    {
      "title": "",
      "media_list_data": [
        
      ],
      "string_list_data": [
        {
          "href": "https://www.instagram.com/alanbruhlee",
          "value": "alanbruhlee",
          "timestamp": 1567729414
        }
      ]
    },
    {
      "title": "",
      "media_list_data": [
        
      ],
      "string_list_data": [
        {
          "href": "https://www.instagram.com/liviaxbeatriz",
          "value": "liviaxbeatriz",
          "timestamp": 1567642605
        }
      ]
    },
    {
      "title": "",
      "media_list_data": [
        
      ],
      "string_list_data": [
        {
          "href": "https://www.instagram.com/franciswhb3",
          "value": "franciswhb3",
          "timestamp": 1567412892
        }
      ]
    },
    {
      "title": "",
      "media_list_data": [
        
      ],
      "string_list_data": [
        {
          "href": "https://www.instagram.com/rooliveira42",
          "value": "rooliveira42",
          "timestamp": 1567260059
        }
      ]
    },
    {
      "title": "",
      "media_list_data": [
        
      ],
      "string_list_data": [
        {
          "href": "https://www.instagram.com/christina_j_kim",
          "value": "christina_j_kim",
          "timestamp": 1567222043
        }
      ]
    },
    {
      "title": "",
      "media_list_data": [
        
      ],
      "string_list_data": [
        {
          "href": "https://www.instagram.com/beatriz3m",
          "value": "beatriz3m",
          "timestamp": 1567164369
        }
      ]
    },
    {
      "title": "",
      "media_list_data": [
        
      ],
      "string_list_data": [
        {
          "href": "https://www.instagram.com/claudiogazaneo",
          "value": "claudiogazaneo",
          "timestamp": 1566781347
        }
      ]
    },
    {
      "title": "",
      "media_list_data": [
        
      ],
      "string_list_data": [
        {
          "href": "https://www.instagram.com/pedrofmbellas",
          "value": "pedrofmbellas",
          "timestamp": 1566425921
        }
      ]
    },
    {
      "title": "",
      "media_list_data": [
        
      ],
      "string_list_data": [
        {
          "href": "https://www.instagram.com/fernando.accioly",
          "value": "fernando.accioly",
          "timestamp": 1566425879
        }
      ]
    },
    {
      "title": "",
      "media_list_data": [
        
      ],
      "string_list_data": [
        {
          "href": "https://www.instagram.com/luana.s.gaspar",
          "value": "luana.s.gaspar",
          "timestamp": 1566350350
        }
      ]
    },
    {
      "title": "",
      "media_list_data": [
        
      ],
      "string_list_data": [
        {
          "href": "https://www.instagram.com/jessica_fy_sun",
          "value": "jessica_fy_sun",
          "timestamp": 1565564111
        }
      ]
    },
    {
      "title": "",
      "media_list_data": [
        
      ],
      "string_list_data": [
        {
          "href": "https://www.instagram.com/_angelicawang_",
          "value": "_angelicawang_",
          "timestamp": 1564685056
        }
      ]
    },
    {
      "title": "",
      "media_list_data": [
        
      ],
      "string_list_data": [
        {
          "href": "https://www.instagram.com/erikay907",
          "value": "erikay907",
          "timestamp": 1563489698
        }
      ]
    },
    {
      "title": "",
      "media_list_data": [
        
      ],
      "string_list_data": [
        {
          "href": "https://www.instagram.com/keithlwc",
          "value": "keithlwc",
          "timestamp": 1560718022
        }
      ]
    },
    {
      "title": "",
      "media_list_data": [
        
      ],
      "string_list_data": [
        {
          "href": "https://www.instagram.com/doubleu.e.i",
          "value": "doubleu.e.i",
          "timestamp": 1558821671
        }
      ]
    },
    {
      "title": "",
      "media_list_data": [
        
      ],
      "string_list_data": [
        {
          "href": "https://www.instagram.com/guilhermebrlima",
          "value": "guilhermebrlima",
          "timestamp": 1555257312
        }
      ]
    },
    {
      "title": "",
      "media_list_data": [
        
      ],
      "string_list_data": [
        {
          "href": "https://www.instagram.com/tinazi",
          "value": "tinazi",
          "timestamp": 1553106813
        }
      ]
    },
    {
      "title": "",
      "media_list_data": [
        
      ],
      "string_list_data": [
        {
          "href": "https://www.instagram.com/amelia.chen",
          "value": "amelia.chen",
          "timestamp": 1552178933
        }
      ]
    },
    {
      "title": "",
      "media_list_data": [
        
      ],
      "string_list_data": [
        {
          "href": "https://www.instagram.com/ju_jara",
          "value": "ju_jara",
          "timestamp": 1548162464
        }
      ]
    },
    {
      "title": "",
      "media_list_data": [
        
      ],
      "string_list_data": [
        {
          "href": "https://www.instagram.com/larywillcox",
          "value": "larywillcox",
          "timestamp": 1548000823
        }
      ]
    },
    {
      "title": "",
      "media_list_data": [
        
      ],
      "string_list_data": [
        {
          "href": "https://www.instagram.com/eiaugusto",
          "value": "eiaugusto",
          "timestamp": 1547255745
        }
      ]
    },
    {
      "title": "",
      "media_list_data": [
        
      ],
      "string_list_data": [
        {
          "href": "https://www.instagram.com/thainacd",
          "value": "thainacd",
          "timestamp": 1547164552
        }
      ]
    },
    {
      "title": "",
      "media_list_data": [
        
      ],
      "string_list_data": [
        {
          "href": "https://www.instagram.com/paula__sanz",
          "value": "paula__sanz",
          "timestamp": 1546328788
        }
      ]
    },
    {
      "title": "",
      "media_list_data": [
        
      ],
      "string_list_data": [
        {
          "href": "https://www.instagram.com/cintiapiubelli",
          "value": "cintiapiubelli",
          "timestamp": 1545925564
        }
      ]
    },
    {
      "title": "",
      "media_list_data": [
        
      ],
      "string_list_data": [
        {
          "href": "https://www.instagram.com/liliansendra",
          "value": "liliansendra",
          "timestamp": 1540890596
        }
      ]
    },
    {
      "title": "",
      "media_list_data": [
        
      ],
      "string_list_data": [
        {
          "href": "https://www.instagram.com/_mycha",
          "value": "_mycha",
          "timestamp": 1540642115
        }
      ]
    },
    {
      "title": "",
      "media_list_data": [
        
      ],
      "string_list_data": [
        {
          "href": "https://www.instagram.com/mairatiemi",
          "value": "mairatiemi",
          "timestamp": 1538279588
        }
      ]
    },
    {
      "title": "",
      "media_list_data": [
        
      ],
      "string_list_data": [
        {
          "href": "https://www.instagram.com/david.zambelli",
          "value": "david.zambelli",
          "timestamp": 1536266772
        }
      ]
    },
    {
      "title": "",
      "media_list_data": [
        
      ],
      "string_list_data": [
        {
          "href": "https://www.instagram.com/napolithaty",
          "value": "napolithaty",
          "timestamp": 1534121405
        }
      ]
    },
    {
      "title": "",
      "media_list_data": [
        
      ],
      "string_list_data": [
        {
          "href": "https://www.instagram.com/andrefyl",
          "value": "andrefyl",
          "timestamp": 1534121151
        }
      ]
    },
    {
      "title": "",
      "media_list_data": [
        
      ],
      "string_list_data": [
        {
          "href": "https://www.instagram.com/the_coelho",
          "value": "the_coelho",
          "timestamp": 1533505400
        }
      ]
    },
    {
      "title": "",
      "media_list_data": [
        
      ],
      "string_list_data": [
        {
          "href": "https://www.instagram.com/mminiwei",
          "value": "mminiwei",
          "timestamp": 1533073537
        }
      ]
    },
    {
      "title": "",
      "media_list_data": [
        
      ],
      "string_list_data": [
        {
          "href": "https://www.instagram.com/anxeeelica",
          "value": "anxeeelica",
          "timestamp": 1532869735
        }
      ]
    },
    {
      "title": "",
      "media_list_data": [
        
      ],
      "string_list_data": [
        {
          "href": "https://www.instagram.com/rafael_jin",
          "value": "rafael_jin",
          "timestamp": 1532826345
        }
      ]
    },
    {
      "title": "",
      "media_list_data": [
        
      ],
      "string_list_data": [
        {
          "href": "https://www.instagram.com/erick_frota",
          "value": "erick_frota",
          "timestamp": 1532741079
        }
      ]
    },
    {
      "title": "",
      "media_list_data": [
        
      ],
      "string_list_data": [
        {
          "href": "https://www.instagram.com/ricoloureiro",
          "value": "ricoloureiro",
          "timestamp": 1532159523
        }
      ]
    },
    {
      "title": "",
      "media_list_data": [
        
      ],
      "string_list_data": [
        {
          "href": "https://www.instagram.com/sunwill_26",
          "value": "sunwill_26",
          "timestamp": 1532082389
        }
      ]
    },
    {
      "title": "",
      "media_list_data": [
        
      ],
      "string_list_data": [
        {
          "href": "https://www.instagram.com/mauriciorigoni",
          "value": "mauriciorigoni",
          "timestamp": 1531873589
        }
      ]
    },
    {
      "title": "",
      "media_list_data": [
        
      ],
      "string_list_data": [
        {
          "href": "https://www.instagram.com/milaa_alves",
          "value": "milaa_alves",
          "timestamp": 1531470718
        }
      ]
    },
    {
      "title": "",
      "media_list_data": [
        
      ],
      "string_list_data": [
        {
          "href": "https://www.instagram.com/matheusferraroni",
          "value": "matheusferraroni",
          "timestamp": 1531261396
        }
      ]
    },
    {
      "title": "",
      "media_list_data": [
        
      ],
      "string_list_data": [
        {
          "href": "https://www.instagram.com/dimitri_muniz",
          "value": "dimitri_muniz",
          "timestamp": 1530410787
        }
      ]
    },
    {
      "title": "",
      "media_list_data": [
        
      ],
      "string_list_data": [
        {
          "href": "https://www.instagram.com/julie_latte",
          "value": "julie_latte",
          "timestamp": 1525639328
        }
      ]
    },
    {
      "title": "",
      "media_list_data": [
        
      ],
      "string_list_data": [
        {
          "href": "https://www.instagram.com/mariavick",
          "value": "mariavick",
          "timestamp": 1522502704
        }
      ]
    },
    {
      "title": "",
      "media_list_data": [
        
      ],
      "string_list_data": [
        {
          "href": "https://www.instagram.com/fernandamlb",
          "value": "fernandamlb",
          "timestamp": 1522272216
        }
      ]
    },
    {
      "title": "",
      "media_list_data": [
        
      ],
      "string_list_data": [
        {
          "href": "https://www.instagram.com/iagoleal13",
          "value": "iagoleal13",
          "timestamp": 1520954156
        }
      ]
    },
    {
      "title": "",
      "media_list_data": [
        
      ],
      "string_list_data": [
        {
          "href": "https://www.instagram.com/alianahuang",
          "value": "alianahuang",
          "timestamp": 1520944521
        }
      ]
    },
    {
      "title": "",
      "media_list_data": [
        
      ],
      "string_list_data": [
        {
          "href": "https://www.instagram.com/bernardogmp",
          "value": "bernardogmp",
          "timestamp": 1520436833
        }
      ]
    },
    {
      "title": "",
      "media_list_data": [
        
      ],
      "string_list_data": [
        {
          "href": "https://www.instagram.com/ricardofang",
          "value": "ricardofang",
          "timestamp": 1520036671
        }
      ]
    },
    {
      "title": "",
      "media_list_data": [
        
      ],
      "string_list_data": [
        {
          "href": "https://www.instagram.com/claricorb",
          "value": "claricorb",
          "timestamp": 1519849565
        }
      ]
    },
    {
      "title": "",
      "media_list_data": [
        
      ],
      "string_list_data": [
        {
          "href": "https://www.instagram.com/vivizsq",
          "value": "vivizsq",
          "timestamp": 1516659221
        }
      ]
    },
    {
      "title": "",
      "media_list_data": [
        
      ],
      "string_list_data": [
        {
          "href": "https://www.instagram.com/andressaspassos",
          "value": "andressaspassos",
          "timestamp": 1515511400
        }
      ]
    },
    {
      "title": "",
      "media_list_data": [
        
      ],
      "string_list_data": [
        {
          "href": "https://www.instagram.com/tawachaan",
          "value": "tawachaan",
          "timestamp": 1514421255
        }
      ]
    },
    {
      "title": "",
      "media_list_data": [
        
      ],
      "string_list_data": [
        {
          "href": "https://www.instagram.com/juujes.psd",
          "value": "juujes.psd",
          "timestamp": 1512742633
        }
      ]
    },
    {
      "title": "",
      "media_list_data": [
        
      ],
      "string_list_data": [
        {
          "href": "https://www.instagram.com/adrianaabreu.fisio",
          "value": "adrianaabreu.fisio",
          "timestamp": 1512352041
        }
      ]
    },
    {
      "title": "",
      "media_list_data": [
        
      ],
      "string_list_data": [
        {
          "href": "https://www.instagram.com/xianyachen",
          "value": "xianyachen",
          "timestamp": 1511305633
        }
      ]
    },
    {
      "title": "",
      "media_list_data": [
        
      ],
      "string_list_data": [
        {
          "href": "https://www.instagram.com/kelly.zhan",
          "value": "kelly.zhan",
          "timestamp": 1509384292
        }
      ]
    },
    {
      "title": "",
      "media_list_data": [
        
      ],
      "string_list_data": [
        {
          "href": "https://www.instagram.com/manjuw_",
          "value": "manjuw_",
          "timestamp": 1509065313
        }
      ]
    },
    {
      "title": "",
      "media_list_data": [
        
      ],
      "string_list_data": [
        {
          "href": "https://www.instagram.com/sabrinac_",
          "value": "sabrinac_",
          "timestamp": 1508846288
        }
      ]
    },
    {
      "title": "",
      "media_list_data": [
        
      ],
      "string_list_data": [
        {
          "href": "https://www.instagram.com/analuluneves",
          "value": "analuluneves",
          "timestamp": 1508704146
        }
      ]
    },
    {
      "title": "",
      "media_list_data": [
        
      ],
      "string_list_data": [
        {
          "href": "https://www.instagram.com/andrehyzn",
          "value": "andrehyzn",
          "timestamp": 1507405484
        }
      ]
    },
    {
      "title": "",
      "media_list_data": [
        
      ],
      "string_list_data": [
        {
          "href": "https://www.instagram.com/bibs_oo",
          "value": "bibs_oo",
          "timestamp": 1507005298
        }
      ]
    },
    {
      "title": "",
      "media_list_data": [
        
      ],
      "string_list_data": [
        {
          "href": "https://www.instagram.com/julieruiz_",
          "value": "julieruiz_",
          "timestamp": 1506264219
        }
      ]
    },
    {
      "title": "",
      "media_list_data": [
        
      ],
      "string_list_data": [
        {
          "href": "https://www.instagram.com/hnk_1104",
          "value": "hnk_1104",
          "timestamp": 1506207350
        }
      ]
    },
    {
      "title": "",
      "media_list_data": [
        
      ],
      "string_list_data": [
        {
          "href": "https://www.instagram.com/niel_ly",
          "value": "niel_ly",
          "timestamp": 1505529836
        }
      ]
    },
    {
      "title": "",
      "media_list_data": [
        
      ],
      "string_list_data": [
        {
          "href": "https://www.instagram.com/camilabiscacio",
          "value": "camilabiscacio",
          "timestamp": 1504964101
        }
      ]
    },
    {
      "title": "",
      "media_list_data": [
        
      ],
      "string_list_data": [
        {
          "href": "https://www.instagram.com/baileyzeng",
          "value": "baileyzeng",
          "timestamp": 1504569313
        }
      ]
    },
    {
      "title": "",
      "media_list_data": [
        
      ],
      "string_list_data": [
        {
          "href": "https://www.instagram.com/nataliawangy",
          "value": "nataliawangy",
          "timestamp": 1504534934
        }
      ]
    },
    {
      "title": "",
      "media_list_data": [
        
      ],
      "string_list_data": [
        {
          "href": "https://www.instagram.com/beatrizfields",
          "value": "beatrizfields",
          "timestamp": 1504307161
        }
      ]
    },
    {
      "title": "",
      "media_list_data": [
        
      ],
      "string_list_data": [
        {
          "href": "https://www.instagram.com/barbaraelmor",
          "value": "barbaraelmor",
          "timestamp": 1504148061
        }
      ]
    },
    {
      "title": "",
      "media_list_data": [
        
      ],
      "string_list_data": [
        {
          "href": "https://www.instagram.com/kewintchen",
          "value": "kewintchen",
          "timestamp": 1504139337
        }
      ]
    },
    {
      "title": "",
      "media_list_data": [
        
      ],
      "string_list_data": [
        {
          "href": "https://www.instagram.com/winwu10",
          "value": "winwu10",
          "timestamp": 1504122776
        }
      ]
    },
    {
      "title": "",
      "media_list_data": [
        
      ],
      "string_list_data": [
        {
          "href": "https://www.instagram.com/joaoguilhermeguida",
          "value": "joaoguilhermeguida",
          "timestamp": 1504120051
        }
      ]
    },
    {
      "title": "",
      "media_list_data": [
        
      ],
      "string_list_data": [
        {
          "href": "https://www.instagram.com/leticia_sueiro",
          "value": "leticia_sueiro",
          "timestamp": 1504108510
        }
      ]
    },
    {
      "title": "",
      "media_list_data": [
        
      ],
      "string_list_data": [
        {
          "href": "https://www.instagram.com/itsjessicaz",
          "value": "itsjessicaz",
          "timestamp": 1504050930
        }
      ]
    },
    {
      "title": "",
      "media_list_data": [
        
      ],
      "string_list_data": [
        {
          "href": "https://www.instagram.com/sprigabi",
          "value": "sprigabi",
          "timestamp": 1503863877
        }
      ]
    },
    {
      "title": "",
      "media_list_data": [
        
      ],
      "string_list_data": [
        {
          "href": "https://www.instagram.com/ayxland",
          "value": "ayxland",
          "timestamp": 1503540954
        }
      ]
    },
    {
      "title": "",
      "media_list_data": [
        
      ],
      "string_list_data": [
        {
          "href": "https://www.instagram.com/gabizftv",
          "value": "gabizftv",
          "timestamp": 1503366871
        }
      ]
    },
    {
      "title": "",
      "media_list_data": [
        
      ],
      "string_list_data": [
        {
          "href": "https://www.instagram.com/yimeichan",
          "value": "yimeichan",
          "timestamp": 1498793455
        }
      ]
    },
    {
      "title": "",
      "media_list_data": [
        
      ],
      "string_list_data": [
        {
          "href": "https://www.instagram.com/camzjin",
          "value": "camzjin",
          "timestamp": 1486398640
        }
      ]
    },
    {
      "title": "",
      "media_list_data": [
        
      ],
      "string_list_data": [
        {
          "href": "https://www.instagram.com/celinelili_",
          "value": "celinelili_",
          "timestamp": 1445193765
        }
      ]
    },
    {
      "title": "",
      "media_list_data": [
        
      ],
      "string_list_data": [
        {
          "href": "https://www.instagram.com/paolamissae",
          "value": "paolamissae",
          "timestamp": 1441636090
        }
      ]
    },
    {
      "title": "",
      "media_list_data": [
        
      ],
      "string_list_data": [
        {
          "href": "https://www.instagram.com/wuiuwu",
          "value": "wuiuwu",
          "timestamp": 1431450156
        }
      ]
    },
    {
      "title": "",
      "media_list_data": [
        
      ],
      "string_list_data": [
        {
          "href": "https://www.instagram.com/hirasawaj",
          "value": "hirasawaj",
          "timestamp": 1430070848
        }
      ]
    },
    {
      "title": "",
      "media_list_data": [
        
      ],
      "string_list_data": [
        {
          "href": "https://www.instagram.com/elisaaa_yy",
          "value": "elisaaa_yy",
          "timestamp": 1426252697
        }
      ]
    },
    {
      "title": "",
      "media_list_data": [
        
      ],
      "string_list_data": [
        {
          "href": "https://www.instagram.com/jingennk",
          "value": "jingennk",
          "timestamp": 1425653454
        }
      ]
    },
    {
      "title": "",
      "media_list_data": [
        
      ],
      "string_list_data": [
        {
          "href": "https://www.instagram.com/llopescamila",
          "value": "llopescamila",
          "timestamp": 1425512195
        }
      ]
    },
    {
      "title": "",
      "media_list_data": [
        
      ],
      "string_list_data": [
        {
          "href": "https://www.instagram.com/juwang_",
          "value": "juwang_",
          "timestamp": 1425494436
        }
      ]
    }
  ]
}